Metadata-Version: 2.1
Name: CustomShell
Version: 0.0.4
Summary: This script implement a Custom Shell.
Home-page: https://github.com/mauricelambert/CustomShell
Author: Maurice Lambert
Author-email: mauricelambert434@gmail.com
License: UNKNOWN
Platform: UNKNOWN
Classifier: Programming Language :: Python
Classifier: Development Status :: 5 - Production/Stable
Classifier: Environment :: Console
Classifier: Natural Language :: English
Classifier: Operating System :: OS Independent
Classifier: Programming Language :: Python :: 3.8
Requires-Python: >=3.6
